tessif/__init__.py
tessif/cli.py
tessif/components.py
tessif/deserialize.py
tessif/frused/__init__.py
tessif/frused/configurations.py
tessif/frused/defaults.py
tessif/frused/namedtuples.py
tessif/frused/paths.py
tessif/frused/resolutions.py
tessif/frused/spellings.py
tessif/frused/themes.py
tessif/frused/utils.py
tessif/hooks/__init__.py
tessif/hooks/ppsa.py
tessif/hooks/tsf.py
tessif/logging.py
tessif/nxgraph.py
tessif/post_process.py
tessif/serialize.py
tessif/system_model.py
tessif/tropp.py
tessif-0.0.28.dist-info/LICENSE
tessif-0.0.28.dist-info/WHEEL
tessif-0.0.28.dist-info/entry_points.txt
tessif-0.0.28.dist-info/METADATA
tessif-0.0.28.dist-info/RECORD
