Metadata-Version: 2.1
Name: tessif
Version: 0.0.28
Summary: Transforming Energy Supply System modell*I*ng Framework
Home-page: https://github.com/tZ3ma/tessif
License: MIT
Keywords: Tessif,tessif,ESSMOS,energy supply system modelling
Author: Mathias Ammon
Author-email: tz3ma.coding@use.startmail.com
Requires-Python: >=3.8,<4.0
Classifier: License :: OSI Approved :: MIT License
Classifier: Programming Language :: Python :: 3
Classifier: Programming Language :: Python :: 3.8
Classifier: Programming Language :: Python :: 3.9
Classifier: Programming Language :: Python :: 3.10
Classifier: Programming Language :: Python :: 3.11
Requires-Dist: click (>7)
Requires-Dist: dcttools (>=0.1.4,<0.2.0)
Requires-Dist: matplotlib (>=3,<4)
Requires-Dist: networkx (>=3,<4)
Requires-Dist: strutils (>=0.1.1,<0.2.0)
Project-URL: Repository, https://github.com/tZ3ma/tessif
